LICENSE
README.md
social_oauth_token/__init__.py
social_oauth_token/apps.py
social_oauth_token/migrations/__init__.py
social_oauth_token/urls.py
social_oauth_token/views.py
django_social_oauth_token-2.2.0.dist-info/LICENSE
django_social_oauth_token-2.2.0.dist-info/WHEEL
django_social_oauth_token-2.2.0.dist-info/METADATA
django_social_oauth_token-2.2.0.dist-info/RECORD
