Metadata-Version: 2.1
Name: django-social-oauth-token
Version: 2.2.0
Summary: OAuth Token generation API for handling OAuth 2.0 Authentication Code Flow based on social-auth
Home-page: https://github.com/khasbilegt/django-social-oauth-token
License: MIT
Keywords: django,model,user,email,username,custom
Author: Khasbilegt.TS
Author-email: khasbilegt.ts@gmail.com
Requires-Python: >=3.6.2,<4.0.0
Classifier: Environment :: Web Environment
Classifier: Framework :: Django
Classifier: Framework :: Django :: 3.2
Classifier: Framework :: Django :: 4.0
Classifier: Intended Audience :: Developers
Classifier: License :: OSI Approved :: MIT License
Classifier: Programming Language :: Python
Classifier: Programming Language :: Python :: 3
Classifier: Programming Language :: Python :: 3.7
Classifier: Programming Language :: Python :: 3.8
Classifier: Programming Language :: Python :: 3.9
Classifier: Programming Language :: Python :: 3.10
Classifier: Programming Language :: Python :: 3.11
Classifier: Programming Language :: Python :: 3.6
Classifier: Programming Language :: Python :: 3.7
Classifier: Programming Language :: Python :: 3.8
Classifier: Programming Language :: Python :: 3.9
Classifier: Topic :: Software Development :: Build Tools
Requires-Dist: django-oauth-toolkit (>=2.1.0,<3.0.0)
Requires-Dist: social-auth-app-django (>=5.0.0,<6.0.0)
Project-URL: Repository, https://github.com/khasbilegt/django-social-oauth-token
